{"interpretations":[{"what":"","where":"asmara eritrea","feature":{"cc":"ER","geometry":{"center":{"lat":15.33805,"lng":38.93184},"bounds":{"ne":{"lat":15.361004,"lng":38.989105},"sw":{"lat":15.300246,"lng":38.898468}},"source":"2-diss-gn-ER.shp"},"name":"Asmara","displayName":"Asmara, Eritrea","woeType":7,"ids":[{"source":"geonameid","id":"343300"},{"source":"woeid","id":"1312120"}],"names":[{"name":"Asmara","lang":"en","flags":[1]}],"highlightedName":"<b>Asmara</b>, <b>Eritrea</b>","matchedName":"Asmara, Eritrea","id":"geonameid:343300","attributes":{"adm0cap":1,"scalerank":3,"labelrank":8,"natscale":110,"population":563930,"urls":["http://ru.wikipedia.org/wiki/%D0%90%D1%81%D0%BC%D1%8D%D1%80%D0%B0","http://en.wikipedia.org/wiki/Asmara"],"worldcity":0},"longId":"72057594038271236","longIds":["72057594044225238"],"parentIds":["72057594038265946","72057594038376437"]}}]}