{"interpretations":[{"what":"","where":"honiara solomon islands","feature":{"cc":"SB","geometry":{"center":{"lat":-9.43333,"lng":159.95},"bounds":{"ne":{"lat":-9.414431,"lng":159.970383},"sw":{"lat":-9.466925,"lng":159.901886}},"source":"2-diss-gn-SB.shp"},"name":"Honiara","displayName":"Honiara, Solomon Islands","woeType":7,"ids":[{"source":"geonameid","id":"2108502"},{"source":"woeid","id":"1020496"}],"names":[{"name":"Honiara","lang":"en","flags":[16,1]}],"highlightedName":"<b>Honiara</b>, <b>Solomon Islands</b>","matchedName":"Honiara, Solomon Islands","id":"geonameid:2108502","attributes":{"adm0cap":1,"scalerank":3,"labelrank":8,"natscale":110,"population":56298,"urls":["http://ru.wikipedia.org/wiki/%D0%A5%D0%BE%D0%BD%D0%B8%D0%B0%D1%80%D0%B0","http://en.wikipedia.org/wiki/Honiara"],"worldcity":0},"longId":"72057594040036438","longIds":["72057594047187003"],"parentIds":["72057594040031286","72057594040036767"]}}]}