{"interpretations":[{"what":"","where":"juba south sudan","feature":{"cc":"SS","geometry":{"center":{"lat":4.85165,"lng":31.58247},"bounds":{"ne":{"lat":4.891546,"lng":31.621828},"sw":{"lat":4.815174,"lng":31.555601}},"source":"2-diss-gn-SD.shp"},"name":"Juba","displayName":"Juba, South Sudan","woeType":7,"ids":[{"source":"geonameid","id":"373303"},{"source":"woeid","id":"1433205"}],"names":[{"name":"Juba","lang":"en","flags":[16,1]}],"highlightedName":"<b>Juba</b>, <b>South Sudan</b>","matchedName":"Juba, South Sudan","id":"geonameid:373303","attributes":{"adm0cap":0,"scalerank":4,"labelrank":5,"natscale":50,"population":300000,"urls":["http://en.wikipedia.org/wiki/Juba_(Southern_Sudan)"],"worldcity":0},"longId":"72057594038301239","longIds":["72057594044225284"],"parentIds":["72057594045837743","72057594038336591"]}}]}