{"interpretations":[{"what":"","where":"mata utu wallis and futuna","feature":{"cc":"WF","geometry":{"center":{"lat":-13.28163,"lng":-176.17453},"bounds":{"ne":{"lat":-13.26952,"lng":-176.129974},"sw":{"lat":-13.285893,"lng":-176.147919}},"source":"2-diss-gn-WF.shp"},"name":"Mata-Utu","displayName":"Mata-Utu, Wallis and Futuna","woeType":7,"ids":[{"source":"geonameid","id":"4034821"}],"names":[{"name":"Mata-Utu","lang":"en","flags":[1]}],"highlightedName":"<b>Mata-Utu</b>, <b>Wallis and Futuna</b>","matchedName":"Mata-Utu, Wallis and Futuna","id":"geonameid:4034821","attributes":{"population":1200,"urls":["http://en.wikipedia.org/wiki/Mata-Utu"]},"longId":"72057594041962757","parentIds":["72057594041962685","72057594041962695"]}}]}